[
    {
        "description": "Turn bathtime into a fun experience with this Da Bomb Bath Fizzers Cake Bomb Bath Soak. It has a luscious almond buttercream scent, and it's white with rainbow sprinkles to replicate the look of a birthday cake. When you drop it into the water, this fizzing bath bomb releases its nourishing ingredients into the water, revealing a special surprise. This bath soak is vegan and cruelty-free, and it contains no phthalates, parabens, sulfates, gluten or nut products.", 
        "dpci": "037-08-2094", 
        "brand": "Da Bomb Bath Fizzers", 
        "tcin": "51236499", 
        "images": [
            {
                "base_url": "https://target.scene7.com/is/image/Target/", 
                "primary": "51236499"
            }
        ], 
        "package_dimensions": "", 
        "categories": [
            "personal care", 
            "Skin care", 
            "Bath bombs"
        ], 
        "title": "Da Bomb Bath Fizzers&#153; Cake Bomb&#153; Bath Soak", 
        "url": "/p/da-bomb-bath-fizzers-153-cake-bomb-153-bath-soak/-/A-51236499", 
        "release_date": "", 
        "upc": "856901006289", 
        "available_to_purchase_date_time": "", 
        "soft_bullets": {
            "bullets": [
                "3.5oz fizzing bath soak provides plenty of fun fizzing action", 
                "Contains soothing oils to leave skin silky", 
                "Bath bomb has a surprise inside, so it makes a great gift"
            ], 
            "title": "highlights"
        }, 
        "bullet_description": [
            "<B>Product Form:</B> bath bomb", 
            "<B>Scent:</B> Scented", 
            "<B>Health Facts:</B> vegan, paraben-free, sodium lauryl sulfate-free, gluten-free, dye-free, fluoride-free, phthalate-free, Sulfate-free, aluminum-free", 
            "<B>Product Warning:</B> no warning applicable", 
            "<B>Container Type:</B> Packet"
        ]
    }, 
    {
        "description": "Flit over to your nearest tub and drop this fanciful fizzer! Drop this 3.5oz sphere into your bath water and watch as it fizzes and spins, releasing skin-soothing ingredients and oils. Hold it in your hand as it dissolves because there's a fun surprise inside. Perfect for adults and kids alike. (Everyone loves surprises.) Created by a pair of teenage sisterpreneurs\u0099. Handmade in the USA using just a few, simple ingredients.", 
        "dpci": "037-08-2316", 
        "brand": "Da Bomb Bath Fizzers", 
        "tcin": "52634970", 
        "images": [
            {
                "content_labels": [
                    {
                        "image_url": "52634970", 
                        "displayed_in_image": {}
                    }
                ], 
                "base_url": "https://target.scene7.com/is/image/Target/", 
                "primary": "52634970"
            }
        ], 
        "package_dimensions": "", 
        "categories": [
            "personal care", 
            "Skin care", 
            "Bath bombs"
        ], 
        "title": "Da Bomb Bath Fizzers - Fairy Bomb", 
        "url": "/p/da-bomb-bath-fizzers-fairy-bomb/-/A-52634970", 
        "release_date": "", 
        "upc": "856901006548", 
        "available_to_purchase_date_time": "", 
        "soft_bullets": {
            "bullets": [
                "Phthalate-free", 
                "Paraben-free", 
                "SLS-free", 
                "Sulfate-free", 
                "Gluten-free", 
                "Nut-free", 
                "Cruelty-free", 
                "Vegan", 
                "WARNING: Small parts. Not for children under 3 years."
            ], 
            "title": "highlights"
        }, 
        "bullet_description": [
            "<B>Product Form:</B> bath bomb", 
            "<B>Scent:</B> Scented", 
            "<B>Health Facts:</B> paraben-free, phthalate-free, Sulfate-free, vegan, dye-free, aluminum-free", 
            "<B>Product Warning:</B> no warning applicable", 
            "<B>Container Type:</B> Packet"
        ]
    }, 
    {
        "description": "Fizz yourself right out of the stratosphere with this delightfully cosmic creation. Drop this 3.5oz sphere into your bath water and watch as it fizzes and spins, releasing skin-soothing ingredients and oils. Hold it in your hand as it dissolves because there's a fun surprise inside. Perfect for adults and kids alike. (Everyone loves surprises.) Created by a pair of teenage sisterpreneurs\u0099. Handmade in the USA using just a few, simple ingredients.", 
        "dpci": "037-08-2315", 
        "brand": "Da Bomb Bath Fizzers", 
        "tcin": "52634958", 
        "images": [
            {
                "content_labels": [
                    {
                        "image_url": "52634958", 
                        "displayed_in_image": {}
                    }
                ], 
                "base_url": "https://target.scene7.com/is/image/Target/", 
                "primary": "52634958"
            }
        ], 
        "package_dimensions": "", 
        "categories": [
            "personal care", 
            "Skin care", 
            "Bath bombs"
        ], 
        "title": "Da Bomb Bath Fizzers - Galaxy Bomb", 
        "url": "/p/da-bomb-bath-fizzers-galaxy-bomb/-/A-52634958", 
        "release_date": "", 
        "upc": "856901006487", 
        "available_to_purchase_date_time": "", 
        "soft_bullets": {
            "bullets": [
                "Phthalate-free", 
                "Paraben-free", 
                "SLS-free", 
                "Sulfate-free", 
                "Gluten-free", 
                "Nut-free", 
                "Cruelty-free", 
                "Vegan", 
                "WARNING: Small parts. Not for children under 3 years."
            ], 
            "title": "highlights"
        }, 
        "bullet_description": [
            "<B>Product Form:</B> bath bomb", 
            "<B>Scent:</B> Scented", 
            "<B>Health Facts:</B> paraben-free, phthalate-free, Sulfate-free, vegan, dye-free, aluminum-free", 
            "<B>Product Warning:</B> no warning applicable", 
            "<B>Container Type:</B> Packet"
        ]
    }, 
    {
        "description": "Make the ocean a better place with every bath you take with Earth Bomb Bath Soak from Da Bomb Bath Fizzers. A portion from each sale is donated to ocean preservation projects. These earth-inspired bath bombs created by sisterpreneurs are designed to fizz up and infuse the bath water with oils and a clean, fresh sea mist scent. Hold the bath bomb in your hand as it fizzes in the water to catch the surprise in the middle.", 
        "dpci": "037-08-2093", 
        "brand": "Da Bomb Bath Fizzers", 
        "tcin": "51236352", 
        "images": [
            {
                "base_url": "https://target.scene7.com/is/image/Target/", 
                "primary": "51236352"
            }
        ], 
        "package_dimensions": "", 
        "categories": [
            "personal care", 
            "Skin care", 
            "Bath bombs"
        ], 
        "title": "Da Bomb Bath Fizzers&#153; Earth Bomb&#153; Bath Soak", 
        "url": "/p/da-bomb-bath-fizzers-153-earth-bomb-153-bath-soak/-/A-51236352", 
        "release_date": "", 
        "upc": "856901006272", 
        "available_to_purchase_date_time": "", 
        "soft_bullets": {
            "bullets": [
                "Makes bathtime fun with a surprise in every bath bomb", 
                "Made with skin-soothing ingredients", 
                "Earth Bombs are cruelty-free and ingredients are vegan"
            ], 
            "title": "highlights"
        }, 
        "bullet_description": [
            "<B>Product Form:</B> bath bomb", 
            "<B>Scent:</B> sea mist, sea minerals", 
            "<B>Health Facts:</B> vegan, paraben-free, sodium lauryl sulfate-free, gluten-free, phthalate-free, Sulfate-free, dye-free, aluminum-free", 
            "<B>Product Warning:</B> no warning applicable", 
            "<B>Container Type:</B> Packet"
        ]
    }, 
    {
        "description": "Put the \"F\" in fizz with the \"F\" Bomb Bath Soak from Da Bomb Bath Fizzers. This wonderful, whimsical bath fizzer is infused with lavender for the ultimate in relaxation while rejuvenating the mind, body and soul. This purple bath bomb dissolves to reveal a calming message perfect at the end of a long day.", 
        "dpci": "037-08-1738", 
        "brand": "Da Bomb Bath Fizzers", 
        "tcin": "51236722", 
        "images": [
            {
                "base_url": "https://target.scene7.com/is/image/Target/", 
                "primary": "51236722"
            }
        ], 
        "package_dimensions": "", 
        "categories": [
            "personal care", 
            "Skin care", 
            "Bath bombs"
        ], 
        "title": "Da Bomb Bath Fizzers&#153; \"F\" Bomb&#153; Bath Soak", 
        "url": "/p/da-bomb-bath-fizzers-153-f-bomb-153-bath-soak/-/A-51236722", 
        "release_date": "", 
        "upc": "856901006265", 
        "available_to_purchase_date_time": "", 
        "soft_bullets": {
            "bullets": [
                "Fun bath bomb dissolves to reveal a calming message", 
                "Lavender scent relaxes and de-stresses", 
                "Skin-soothing ingredients leave your skin soft"
            ], 
            "title": "highlights"
        }, 
        "bullet_description": [
            "<B>Product Form:</B> bath bomb", 
            "<B>Scent:</B> Lavender", 
            "<B>Health Facts:</B> vegan, paraben-free, sodium lauryl sulfate-free, gluten-free, dye-free, fluoride-free, phthalate-free, Sulfate-free, aluminum-free", 
            "<B>Product Warning:</B> no warning applicable", 
            "<B>Container Type:</B> Packet"
        ]
    }, 
    {
        "description": "It's love at first fizz when you drop this fragrant bath bomb into your tub. Watch as this 3.5oz sphere fizzes and spins, releasing skin-soothing ingredients and oils. Hold it in your hand as it dissolves because there's a fun surprise inside. Perfect for adults and kids alike. (Everyone loves surprises.) Created by a pair of teenage sisterpreneurs\u0099. Handmade in the USA using just a few, simple ingredients.", 
        "dpci": "037-08-2317", 
        "brand": "Da Bomb Bath Fizzers", 
        "tcin": "52634922", 
        "images": [
            {
                "content_labels": [
                    {
                        "image_url": "52634922", 
                        "displayed_in_image": {}
                    }
                ], 
                "base_url": "https://target.scene7.com/is/image/Target/", 
                "primary": "52634922"
            }
        ], 
        "package_dimensions": "", 
        "categories": [
            "personal care", 
            "Skin care", 
            "Bath bombs"
        ], 
        "title": "Da Bomb Bath Fizzers - Love Bomb", 
        "url": "/p/da-bomb-bath-fizzers-love-bomb/-/A-52634922", 
        "release_date": "", 
        "upc": "856901006500", 
        "available_to_purchase_date_time": "", 
        "soft_bullets": {
            "bullets": [
                "Phthalate-free", 
                "Paraben-free", 
                "SLS-free", 
                "Sulfate-free", 
                "Gluten-free", 
                "Nut-free", 
                "Cruelty-free", 
                "Vegan", 
                "WARNING: Small parts. Not for children under 3 years."
            ], 
            "title": "highlights"
        }, 
        "bullet_description": [
            "<B>Product Form:</B> bath bomb", 
            "<B>Scent:</B> Scented", 
            "<B>Health Facts:</B> paraben-free, phthalate-free, Sulfate-free, vegan, dye-free, aluminum-free", 
            "<B>Product Warning:</B> no warning applicable", 
            "<B>Container Type:</B> Packet"
        ]
    }, 
    {
        "description": "With ME! Bath Lavender Mini Ice Cream Bath Soak, your bath will be as wonderful as ice cream on a hot day. Each mini bath ice cream moisturizes and softens skins using high-quality botanical oils and purifying minerals, soothing sore muscles and washing the day's stress away. The calming lavender scent will relax your body and mind until you forget about the day's worries and enter a state of blissful calm.", 
        "dpci": "037-08-1391", 
        "brand": "Me! Bath", 
        "tcin": "16602281", 
        "images": [
            {
                "base_url": "https://target.scene7.com/is/image/Target/", 
                "primary": "16602281"
            }
        ], 
        "package_dimensions": "", 
        "categories": [
            "personal care", 
            "Skin care", 
            "Bath bombs"
        ], 
        "title": "ME! Bath&#174; Lavender Mini Ice Cream Bath Soak - 12oz", 
        "url": "/p/me-bath-174-lavender-mini-ice-cream-bath-soak-12oz/-/A-16602281", 
        "release_date": "", 
        "upc": "858858000297", 
        "available_to_purchase_date_time": "", 
        "soft_bullets": {
            "bullets": [
                "Moisturizes and softens skin with botanical oils and purifying minerals", 
                "Lavender scent soothes the body and relaxes the mind", 
                "Enough for 6 decadent and relaxing soaks"
            ], 
            "title": "highlights"
        }, 
        "bullet_description": [
            "<B>Product Form:</B> bath bomb", 
            "<B>Package Quantity:</B> 1", 
            "<B>Scent:</B> Lavender", 
            "<B>Health Facts:</B> fluoride-free, vegan, paraben-free, aluminum-free", 
            "<B>Product Warning:</B> no warning applicable", 
            "<B>Container Type:</B> Packet"
        ]
    }, 
    {
        "description": "Make your bath a fun and pampering experience with the Tini Me Bath Bomb Gotta Have It Pomegranate from Me! Bath. This fun, fruity pomegranate bath bomb fizzes when you add it to water, creating a luxurious experience you're sure to love. Enriched with bergamot oil and epsom salt, this soothing bath fizzer treats your skin to a rejuvenating, moisturizing soak. This trial-size container comes with enough scoopable bath soak for two foamy, relaxing experiences.", 
        "dpci": "037-08-1221", 
        "brand": "Me! Bath", 
        "tcin": "23944847", 
        "images": [
            {
                "base_url": "https://target.scene7.com/is/image/Target/", 
                "primary": "23944847"
            }
        ], 
        "package_dimensions": "", 
        "categories": [
            "personal care", 
            "Skin care", 
            "Bath bombs"
        ], 
        "title": "Me! Bath Tini Me Bath Bomb Gotta Have It Pomegranate 2 ct", 
        "url": "/p/me-bath-tini-me-bath-bomb-gotta-have-it-pomegranate-2-ct/-/A-23944847", 
        "release_date": "", 
        "upc": "852394006041", 
        "available_to_purchase_date_time": "", 
        "soft_bullets": {
            "bullets": [
                "Moisturizing bath soak fizzes in the water", 
                "Creates a fun and indulgent spa experience in your own home", 
                "Features natural ingredients and epsom salt to draw out impurities", 
                "Delicious pomegranate scent"
            ], 
            "title": "highlights"
        }, 
        "bullet_description": [
            "<B>Product Form:</B> bath bomb", 
            "<B>Scent:</B> pomegranate, Lavender", 
            "<B>Health Facts:</B> vegan, paraben-free, aluminum-free", 
            "<B>Product Warning:</B> no warning applicable", 
            "<B>Container Type:</B> Packet"
        ]
    }, 
    {
        "description": "ME! Bath Birthday Cake Mini Bath Ice Cream Bath Soak offers a perfect way to relax after a long day. Create an at-home spa experience with the delicious smells of yellow birthday cake and buttery vanilla frosting.", 
        "dpci": "037-08-1844", 
        "brand": "Me! Bath", 
        "tcin": "50918523", 
        "images": [
            {
                "base_url": "https://target.scene7.com/is/image/Target/", 
                "primary": "50918523"
            }
        ], 
        "package_dimensions": "", 
        "categories": [
            "personal care", 
            "Skin care", 
            "Bath bombs"
        ], 
        "title": "ME! Bath&#174; Birthday Cake Mini Ice Cream Bath Soak - 12oz", 
        "url": "/p/me-bath-174-birthday-cake-mini-ice-cream-bath-soak-12oz/-/A-50918523", 
        "release_date": "", 
        "upc": "852394006133", 
        "available_to_purchase_date_time": "", 
        "soft_bullets": {
            "bullets": [
                "6 bath bombs handmade in small batches", 
                "6 oil blend: sweet almond oil, jojoba oil, coconut oil, macadamia oil, sesame oil and sunflower seed oil", 
                "Purifying minerals and Epsom salt to hydrate, moisturize and nourish the skin", 
                "Colorful rainbow sprinkles"
            ], 
            "title": "highlights"
        }, 
        "bullet_description": [
            "<B>Product Form:</B> bath bomb", 
            "<B>Scent:</B> cotton candy", 
            "<B>Health Facts:</B> vegan, paraben-free, aluminum-free", 
            "<B>Product Warning:</B> no warning applicable", 
            "<B>Container Type:</B> Packet"
        ]
    }, 
    {
        "description": "ME! Bath Cucumber Melon Mini Bath Ice Cream Bath Soak offers a perfect way to relax after a long day. Create an at-home spa experience with their light, fresh scent of cucumbers, melon, apple, pear and cyclamen.", 
        "dpci": "037-08-1393", 
        "brand": "Me! Bath", 
        "tcin": "47906187", 
        "images": [
            {
                "base_url": "https://target.scene7.com/is/image/Target/", 
                "primary": "47906187"
            }
        ], 
        "package_dimensions": "", 
        "categories": [
            "personal care", 
            "Skin care", 
            "Bath bombs"
        ], 
        "title": "Me! Bath&#174; Cucumber Melon Mini Bath Ice Cream Bath Soak - 12oz", 
        "url": "/p/me-bath-174-cucumber-melon-mini-bath-ice-cream-bath-soak-12oz/-/A-47906187", 
        "release_date": "", 
        "upc": "852394006157", 
        "available_to_purchase_date_time": "", 
        "soft_bullets": {
            "bullets": [
                "6 bath bombs handmade in small batches", 
                "6 oil blend: sweet almond oil, jojoba oil, coconut oil, macadamia oil, sesame oil and sunflower seed oil", 
                "Purifying minerals and Epsom salt to hydrate, moisturize and nourish the skin", 
                "Relaxes aching muscles and joints"
            ], 
            "title": "highlights"
        }, 
        "bullet_description": [
            "<B>Product Form:</B> bath bomb", 
            "<B>Scent:</B> cucumber, melon", 
            "<B>Health Facts:</B> vegan, paraben-free, aluminum-free", 
            "<B>Product Warning:</B> no warning applicable", 
            "<B>Container Type:</B> Packet"
        ]
    }, 
    {
        "description": "With ME! Bath Pomegranate Mini Ice Cream Bath Soak, your bath will be as wonderful as ice cream on a hot day. Each mini bath ice cream moisturizes and softens skins using high-quality botanical oils and purifying minerals, soothing sore muscles and washing the day's stress away. The pomegranate scent will whisk you to romantic fantasy, perfect for a much-needed escape.", 
        "dpci": "037-08-1390", 
        "brand": "Me! Bath", 
        "tcin": "16602279", 
        "images": [
            {
                "base_url": "https://target.scene7.com/is/image/Target/", 
                "primary": "16602279"
            }
        ], 
        "package_dimensions": "", 
        "categories": [
            "personal care", 
            "Skin care", 
            "Bath bombs"
        ], 
        "title": "ME! Bath&#174; Pomegranate Mini Ice Cream Bath Soak - 12oz", 
        "url": "/p/me-bath-174-pomegranate-mini-ice-cream-bath-soak-12oz/-/A-16602279", 
        "release_date": "", 
        "upc": "858858000433", 
        "available_to_purchase_date_time": "", 
        "soft_bullets": {
            "bullets": [
                "Moisturizes and softens skin with botanical oils and purifying minerals", 
                "Soothes sore muscles and washes stress away", 
                "Luscious pomegranate scent has long been associated with love potions", 
                "Enough for 6 decadent and relaxing soaks"
            ], 
            "title": "highlights"
        }, 
        "bullet_description": [
            "<B>Product Form:</B> bath bomb", 
            "<B>Package Quantity:</B> 1", 
            "<B>Scent:</B> pomegranate", 
            "<B>Health Facts:</B> fluoride-free, vegan, paraben-free, aluminum-free", 
            "<B>Product Warning:</B> no warning applicable", 
            "<B>Container Type:</B> Packet"
        ]
    }, 
    {
        "description": "ME! Bath Love Me! Mini Ice Cream Bath Soak offers a perfect way to relax after a long day. Create an at-home spa experience with their sweet, fruity scent mixed with notes of coconut milk, vanilla, precious woods and musk.", 
        "dpci": "037-08-1843", 
        "brand": "Me! Bath", 
        "tcin": "50918519", 
        "images": [
            {
                "base_url": "https://target.scene7.com/is/image/Target/", 
                "primary": "50918519"
            }
        ], 
        "package_dimensions": "", 
        "categories": [
            "personal care", 
            "Skin care", 
            "Bath bombs"
        ], 
        "title": "ME! Bath&#174; Love Me! Mini Ice Cream Bath Soak - 12oz", 
        "url": "/p/me-bath-174-love-me-mini-ice-cream-bath-soak-12oz/-/A-50918519", 
        "release_date": "", 
        "upc": "852394006140", 
        "available_to_purchase_date_time": "", 
        "soft_bullets": {
            "bullets": [
                "6 bath bombs handmade in small batches", 
                "6 oil blend: sweet almond oil, jojoba oil, coconut oil, macadamia oil, sesame oil and sunflower seed oil", 
                "Purifying minerals and Epsom salt to hydrate, moisturize and nourish the skin", 
                "Mica adds a soft shimmer to the water"
            ], 
            "title": "highlights"
        }, 
        "bullet_description": [
            "<B>Product Form:</B> bath bomb", 
            "<B>Scent:</B> berry", 
            "<B>Health Facts:</B> contains coconut, paraben-free, aluminum-free", 
            "<B>Product Warning:</B> no warning applicable", 
            "<B>Container Type:</B> Packet"
        ]
    }, 
    {
        "description": "We\u2019re bubbling over with excitement about our effervescent bath bomb. Soap & Glory's FIZZ-A-BALL\u0099 is a super-relaxing unbelievably fun treat that bubbles away on contact with water: simply drop it into the bath and jump in after it. Watch the bathwater turn shimmery as the fizzy gets busy. This bath bomb comes in Soap & Glory's signature ORIGINAL PINK fragrance, which features scents of rose and bergamot for pure pampering.", 
        "dpci": "052-12-0709", 
        "brand": "Soap & Glory", 
        "tcin": "52462454", 
        "images": [
            {
                "alternate_urls": [
                    "52462454_Alt02"
                ], 
                "base_url": "https://target.scene7.com/is/image/Target/", 
                "content_labels": [
                    {
                        "image_url": "52462454", 
                        "displayed_in_image": {}
                    }, 
                    {
                        "image_url": "52462454_Alt02", 
                        "displayed_in_image": {}
                    }
                ], 
                "primary": "52462454"
            }
        ], 
        "package_dimensions": "", 
        "categories": [
            "personal care", 
            "Skin care", 
            "Bath bombs"
        ], 
        "title": "Soap & Glory Fizz-A-Ball Bath Bomb Original Pink - 3.5oz", 
        "url": "/p/soap-glory-fizz-a-ball-bath-bomb-original-pink-3-5oz/-/A-52462454", 
        "release_date": "", 
        "upc": "5045096952920", 
        "available_to_purchase_date_time": "", 
        "soft_bullets": {
            "bullets": [
                "Effervescent bath bomb", 
                "Bubbles away on contact with water", 
                "Features Soap & Glory's ORIGINAL PINK fragrance", 
                "A super-relaxing unbelievably fun treat!"
            ], 
            "title": "highlights"
        }, 
        "bullet_description": [
            "<B>Product Form:</B> bath bomb", 
            "<B>Scent:</B> Mandarin, Musk, peach, strawberry, rose, Jasmine", 
            "<B>Health Concern:</B> Stress", 
            "<B>Product Warning:</B> Adult Use Only", 
            "<B>Container Type:</B> Packet"
        ]
    }, 
    {
        "description": "We\u2019re bubbling over with excitement about our effervescent bath bomb. Soap & Glory's FIZZ-A-BALL\u0099 is a super-relaxing unbelievably fun treat that bubbles away on contact with water: simply drop it into the bath and jump in after it. Watch the bathwater turn shimmery as the fizzy gets busy. This bath bomb comes in Soap & Glory's SMOOTHIE STAR fragrance, which features a sweet vanilla musk scent for relaxation.", 
        "dpci": "052-12-0754", 
        "brand": "Soap & Glory", 
        "tcin": "52462474", 
        "images": [
            {
                "alternate_urls": [
                    "52462474_Alt02"
                ], 
                "base_url": "https://target.scene7.com/is/image/Target/", 
                "content_labels": [
                    {
                        "image_url": "52462474", 
                        "displayed_in_image": {}
                    }, 
                    {
                        "image_url": "52462474_Alt02", 
                        "displayed_in_image": {}
                    }
                ], 
                "primary": "52462474"
            }
        ], 
        "package_dimensions": "", 
        "categories": [
            "personal care", 
            "Skin care", 
            "Bath bombs"
        ], 
        "title": "Soap & Glory Fizz-A-Ball Bath Bomb Smoothie Star - 3.5oz", 
        "url": "/p/soap-glory-fizz-a-ball-bath-bomb-smoothie-star-3-5oz/-/A-52462474", 
        "release_date": "", 
        "upc": "5045096952944", 
        "available_to_purchase_date_time": "", 
        "soft_bullets": {
            "bullets": [
                "Effervescent bath bomb", 
                "Bubbles away on contact with water", 
                "Features Soap & Glory's SMOOTHIE STAR fragrance", 
                "A super-relaxing unbelievably fun treat!"
            ], 
            "title": "highlights"
        }, 
        "bullet_description": [
            "<B>Product Form:</B> bath bomb", 
            "<B>Scent:</B> pistachio, almond, vanilla", 
            "<B>Health Concern:</B> Stress", 
            "<B>Product Warning:</B> Adult Use Only", 
            "<B>Features:</B> Non-drying", 
            "<B>Container Type:</B> Packet"
        ]
    }, 
    {
        "description": "We\u2019re bubbling over with excitement about our effervescent bath bomb. Soap & Glory's FIZZ-A-BALL\u0099 is a super-relaxing unbelievably fun treat that bubbles away on contact with water: simply drop it into the bath and jump in after it. Watch the bathwater turn shimmery as the fizzy gets busy. This bath bomb comes in Soap & Glory's SUGAR CRUSH fragrance, which features a sweet lime zest scent for a revitalizing fling with the ultimate zing.", 
        "dpci": "052-12-0733", 
        "brand": "Soap & Glory", 
        "tcin": "52462470", 
        "images": [
            {
                "alternate_urls": [
                    "52462470_Alt02"
                ], 
                "base_url": "https://target.scene7.com/is/image/Target/", 
                "content_labels": [
                    {
                        "image_url": "52462470_Alt02", 
                        "displayed_in_image": {}
                    }, 
                    {
                        "image_url": "52462470", 
                        "displayed_in_image": {}
                    }
                ], 
                "primary": "52462470"
            }
        ], 
        "package_dimensions": "", 
        "categories": [
            "personal care", 
            "Skin care", 
            "Bath bombs"
        ], 
        "title": "Soap & Glory Fizz-A-Ball Bath Bomb Sugar Crush - 3.5oz", 
        "url": "/p/soap-glory-fizz-a-ball-bath-bomb-sugar-crush-3-5oz/-/A-52462470", 
        "release_date": "", 
        "upc": "5045096952937", 
        "available_to_purchase_date_time": "", 
        "soft_bullets": {
            "bullets": [
                "Effervescent bath bomb", 
                "Bubbles away on contact with water", 
                "Features Soap & Glory's SUGAR CRUSH fragrance", 
                "A super-relaxing unbelievably fun treat!"
            ], 
            "title": "highlights"
        }, 
        "bullet_description": [
            "<B>Product Form:</B> bath bomb", 
            "<B>Scent:</B> lemon, lime, vanilla, Musk", 
            "<B>Health Concern:</B> Stress", 
            "<B>Product Warning:</B> Adult Use Only", 
            "<B>Container Type:</B> Packet"
        ]
    }, 
    {
        "description": "Relax and unwind in a luxurious bath with lavender and chamomile essential oils and nourishing shea and cocoa butters. Calm Double Butter Bath Melts by Village Naturals Aromatherapy will hydrate and condition your skin with a rich blend of antioxidants and vitamins c & e. Go ahead\u2026indulge your senses.", 
        "dpci": "037-08-2285", 
        "brand": "Village Naturals", 
        "tcin": "52597396", 
        "images": [
            {
                "content_labels": [
                    {
                        "image_url": "52597396", 
                        "displayed_in_image": {}
                    }
                ], 
                "base_url": "https://target.scene7.com/is/image/Target/", 
                "primary": "52597396"
            }
        ], 
        "package_dimensions": "", 
        "categories": [
            "personal care", 
            "Skin care", 
            "Bath bombs"
        ], 
        "title": "Village Naturals Double Butter Bath Melts - Calm Lavender-Chamomile - 4.9oz", 
        "url": "/p/village-naturals-double-butter-bath-melts-calm-lavender-chamomile-4-9oz/-/A-52597396", 
        "release_date": "", 
        "upc": "735303587001", 
        "available_to_purchase_date_time": "", 
        "soft_bullets": {
            "bullets": [
                "Calm your senses with a luxurious bath", 
                "Double Butter Bath Melts provide a sophisticated experience", 
                "Drench yourself in She and Cocoa Butters that condition and hydrate skin", 
                "Relax and unwind with Lavender & Chamomile essential oils and extracts"
            ], 
            "title": "highlights"
        }, 
        "bullet_description": [
            "<B>Number of Pieces:</B> 2", 
            "<B>Product Form:</B> bath bomb", 
            "<B>Scent:</B> Lavender, chamomile", 
            "<B>Health Facts:</B> paraben-free, aluminum-free", 
            "<B>Product Warning:</B> no warning applicable", 
            "<B>Container Type:</B> Box"
        ]
    }, 
    {
        "description": "Relax and indulge in a soothing, moisturizing bath with Bubbletini Bath Bombs from Luxe by Mr. Bubble. Just place a few under running water and let the day drift away as the luscious sugar cream scent of Sweet & Clean fills the tub, while nourishing ingredients like shea butter leave your skin feeling silky soft. Once you've given yourself some much needed \"me time\", use the shaker to mix up your favorite drink.", 
        "dpci": "037-08-1912", 
        "brand": "Luxe", 
        "tcin": "51114700", 
        "images": [
            {
                "base_url": "https://target.scene7.com/is/image/Target/", 
                "primary": "51114700"
            }
        ], 
        "package_dimensions": "", 
        "categories": [
            "personal care", 
            "Skin care", 
            "Bath bombs"
        ], 
        "title": "Luxe by Mr. Bubble&#174; Sweet & Clean Bubbletini Bath Bombs - 7oz", 
        "url": "/p/luxe-by-mr-bubble-174-sweet-clean-bubbletini-bath-bombs-7oz/-/A-51114700", 
        "release_date": "", 
        "upc": "735303331024", 
        "available_to_purchase_date_time": "", 
        "soft_bullets": {
            "bullets": [
                "Made with shea butter to keep your skin feeling soft and moisturized", 
                "Martini shaker bottle makes it perfect for gifting", 
                "Sugar cream scent sweetens bath time for ultimate relaxation"
            ], 
            "title": "highlights"
        }, 
        "bullet_description": [
            "<B>Number of Pieces:</B> 12", 
            "<B>Product Form:</B> bath bomb", 
            "<B>Scent:</B> Scented", 
            "<B>Health Facts:</B> fluoride-free, paraben-free, aluminum-free", 
            "<B>Product Warning:</B> no warning applicable", 
            "<B>Container Type:</B> Jar"
        ]
    }, 
    {
        "description": "Meltaway Bath Candies are a sweet treat without the calories! Indulge in an ultra-moisturizing soak with Cocoa and Shea Butter bath candies. Infused with the nostalgic fragrance of Original Bubble and enriched with nourishing Vitamins E and C that will leave your skin silky and hydrated. A little me time is delicious, so go ahead and meltaway!", 
        "dpci": "037-08-2283", 
        "brand": "Luxe", 
        "tcin": "52591968", 
        "images": [
            {
                "content_labels": [
                    {
                        "image_url": "52591968", 
                        "displayed_in_image": {}
                    }
                ], 
                "base_url": "https://target.scene7.com/is/image/Target/", 
                "primary": "52591968"
            }
        ], 
        "package_dimensions": "", 
        "categories": [
            "personal care", 
            "Skin care", 
            "Bath bombs"
        ], 
        "title": "Luxe Melt-A-Ways Cocoa & Shea Butter Bath Candies - Original Bubble - 5.29oz", 
        "url": "/p/luxe-melt-a-ways-cocoa-shea-butter-bath-candies-original-bubble-5-29oz/-/A-52591968", 
        "release_date": "", 
        "upc": "735303337170", 
        "available_to_purchase_date_time": "", 
        "soft_bullets": {
            "bullets": [
                "Melt- A-Way in a luxurious bath with Luxe by Mr. Bubble", 
                "A sweet treat without the calories", 
                "Ultra-moisturizing bath candies made with Cocoa and Shea Butters", 
                "Nourish your skin with Vitamins E and C", 
                "Soak in the nostalgia of the Original Bubble fragrance"
            ], 
            "title": "highlights"
        }, 
        "bullet_description": [
            "<B>Number of Pieces:</B> 20", 
            "<B>Product Form:</B> bath bomb", 
            "<B>Scent:</B> Scented", 
            "<B>Health Facts:</B> paraben-free, aluminum-free", 
            "<B>Product Warning:</B> no warning applicable", 
            "<B>Container Type:</B> Box"
        ]
    }, 
    {
        "description": "Me! Bath Bath Bomb Land of Milk n' Honey 6 ct is a great idea to add to a spa gift basket. These bath bombs are like scoops for your bath to make mini bath ice cream that gives you super soft skin.", 
        "dpci": "037-08-0620", 
        "brand": "Me! Bath", 
        "tcin": "18828572", 
        "images": [
            {
                "base_url": "https://target.scene7.com/is/image/Target/", 
                "primary": "18828572"
            }
        ], 
        "package_dimensions": "", 
        "categories": [
            "personal care", 
            "Skin care", 
            "Bath bombs"
        ], 
        "title": "Me! Bath Bath Bomb Land of Milk n' Honey 6 ct", 
        "url": "/p/me-bath-bath-bomb-land-of-milk-n-honey-6-ct/-/A-18828572", 
        "release_date": "", 
        "upc": "858858000198", 
        "available_to_purchase_date_time": "", 
        "soft_bullets": {
            "bullets": [
                "Bath bomb", 
                "6 count"
            ], 
            "title": "highlights"
        }, 
        "bullet_description": [
            "<B>Product Form:</B> bath bomb", 
            "<B>Scent:</B> honey", 
            "<B>Health Facts:</B> fluoride-free, vegan, paraben-free, aluminum-free", 
            "<B>Product Warning:</B> no warning applicable", 
            "<B>Container Type:</B> Packet"
        ]
    }, 
    {
        "description": "", 
        "dpci": "037-08-2273", 
        "brand": "Raw Sugar", 
        "tcin": "52529508", 
        "images": [
            {
                "alternate_urls": [
                    "52529508_Alt01", 
                    "52529508_Alt02"
                ], 
                "swatch": "52529508_Swatch", 
                "base_url": "https://target.scene7.com/is/image/Target/", 
                "content_labels": [
                    {
                        "image_url": "52529508_Alt02", 
                        "displayed_in_image": {}
                    }, 
                    {
                        "image_url": "52529508_Swatch", 
                        "displayed_in_image": {}
                    }, 
                    {
                        "image_url": "52529508_Alt01", 
                        "displayed_in_image": {}
                    }, 
                    {
                        "image_url": "52529508", 
                        "displayed_in_image": {}
                    }
                ], 
                "primary": "52529508"
            }
        ], 
        "package_dimensions": "", 
        "categories": [
            "personal care", 
            "Skin care", 
            "Bath bombs"
        ], 
        "title": "Raw Sugar Cube Bath Fizzers - Pineapple Maqui Berry Coconut Bath Bomb - 4ct", 
        "url": "/p/raw-sugar-cube-bath-fizzers-pineapple-maqui-berry-coconut-bath-bomb-4ct/-/A-52529508", 
        "release_date": "", 
        "upc": "895697005779", 
        "available_to_purchase_date_time": "", 
        "soft_bullets": {}, 
        "bullet_description": [
            "<B>Product Form:</B> bath bomb", 
            "<B>Scent:</B> pineapple, berry, coconut", 
            "<B>Health Facts:</B> butylparaben-free, propylparaben-free, fluoride-free, formaldehyde donor-free, hypoallergenic, contains naturally derived ingredients, animal by-product-free, vegan, paraben-free, phthalate-free, sodium lauryl sulfate-free, non-toxic, Sulfate-free, Talcum-free, contains coconut, contains coconut milk, contains coconut oil, contains eucalyptus, DMDM Hydantoin-free, ethyl alcohol-free, gluten-free, lanolin-free, mineral oil-free, Petroleum-free, aluminum-free", 
            "<B>Health Concern:</B> Stress", 
            "<B>Product Warning:</B> no warning applicable", 
            "<B>Features:</B> Non-irritating, Nongreasy, Soothing, safe to use on sensitive skin", 
            "<B>Container Type:</B> Box"
        ]
    }, 
    {
        "description": "Raw Sugar Bath Fizzer: Raw Coconut + Mango<br><br>Your bath is calling!! Relax everything with this cool cube of bath fizzy goodness. Dip into an invigorating and mood-lifting soak that will leave your skin and mind feeling nourished and refreshed. Packed into each of these \"Raw Sugar Cube\" Fizzers is a sensational explosion of 12 essential oils. The extracts of Raw Coconut with protecting and moisturizing skin benefits, and Mango, loaded with Vitamin A, to promote a healthy sun-kissed glow. These, combined with the perfect amount of Kaolin Clay, Lavender Sea Kelp and Ginger, is oh so gently the flawless blend for purifying your skin.<br><br>Processed through ColdPress Technology\u00ae and infused with Certified Organic Extracts to lock in all that is pure, this wholesome bath fizzer is bubbling with nutrients-just add water-and soak!<br><br>Consciously crafted in sunny Southern California, these Cold-Pressed Bath Fizzers nature your skin and soak your senses with nature's most purifying ingredients-fruits, plants and essential goodness.<br><br>Get the goods that give back-A clean world starts at home, so as part of the Raw Sugar Initiative-a fresh bar of soap is donated to a family in need for every product sold.", 
        "dpci": "037-08-2271", 
        "brand": "Raw Sugar", 
        "tcin": "52529362", 
        "images": [
            {
                "alternate_urls": [
                    "52529362_Alt01", 
                    "52529362_Alt02"
                ], 
                "swatch": "52529362_Swatch", 
                "base_url": "https://target.scene7.com/is/image/Target/", 
                "content_labels": [
                    {
                        "image_url": "52529362_Alt02", 
                        "displayed_in_image": {}
                    }, 
                    {
                        "image_url": "52529362", 
                        "displayed_in_image": {}
                    }, 
                    {
                        "image_url": "52529362_Alt01", 
                        "displayed_in_image": {}
                    }, 
                    {
                        "image_url": "52529362_Swatch", 
                        "displayed_in_image": {}
                    }
                ], 
                "primary": "52529362"
            }
        ], 
        "package_dimensions": "", 
        "categories": [
            "personal care", 
            "Skin care", 
            "Bath bombs"
        ], 
        "title": "Raw Sugar Cube Bath Fizzers - Raw Coconut Mango Bath Bomb - 4ct", 
        "url": "/p/raw-sugar-cube-bath-fizzers-raw-coconut-mango-bath-bomb-4ct/-/A-52529362", 
        "release_date": "", 
        "upc": "895697005755", 
        "available_to_purchase_date_time": "", 
        "soft_bullets": {
            "bullets": [
                "Sulfate-Free", 
                "Paraben-Free", 
                "Certified Organic Extracts", 
                "Cruelty-Free", 
                "Vegan-Free"
            ], 
            "title": "highlights"
        }, 
        "bullet_description": [
            "<B>Product Form:</B> bath bomb", 
            "<B>Scent:</B> coconut, mango", 
            "<B>Health Facts:</B> fluoride-free, formaldehyde donor-free, formaldehyde-free, hypoallergenic, contains naturally derived ingredients, animal by-product-free, vegan, paraben-free, phthalate-free, sodium lauryl sulfate-free, non-toxic, contains coconut, contains coconut milk, contains coconut oil, contains eucalyptus, DMDM Hydantoin-free, ethyl alcohol-free, gluten-free, lanolin-free, mineral oil-free, Petroleum-free, Sulfate-free, Talcum-free, aluminum-free", 
            "<B>Health Concern:</B> Stress", 
            "<B>Product Warning:</B> no warning applicable", 
            "<B>Features:</B> Soothing, Non-irritating, Nongreasy, safe to use on sensitive skin", 
            "<B>Container Type:</B> Box"
        ]
    }, 
    {
        "description": "Relax and indulge in a soothing, moisturizing bath with Bubbletini Bath Bombs from Luxe by Mr. Bubble. Just place a few under running water and let the day drift away as the classic bubble scent fills the tub, while nourishing ingredients like shea butter leave your skin feeling silky soft. Once you've given yourself some much needed \"me time\", use the shaker to mix up your favorite drink.", 
        "dpci": "037-08-1910", 
        "brand": "Luxe", 
        "tcin": "51114564", 
        "images": [
            {
                "base_url": "https://target.scene7.com/is/image/Target/", 
                "primary": "51114564"
            }
        ], 
        "package_dimensions": "", 
        "categories": [
            "personal care", 
            "Skin care", 
            "Bath bombs"
        ], 
        "title": "Luxe by Mr. Bubble&#174; Original Bubbletini Bath Bombs - 7oz", 
        "url": "/p/luxe-by-mr-bubble-174-original-bubbletini-bath-bombs-7oz/-/A-51114564", 
        "release_date": "", 
        "upc": "735303331017", 
        "available_to_purchase_date_time": "", 
        "soft_bullets": {
            "bullets": [
                "Made with shea butter to keep your skin feeling soft and moisturized", 
                "Martini shaker bottle makes it perfect for gifting", 
                "Classic scent adds a relaxing vibe"
            ], 
            "title": "highlights"
        }, 
        "bullet_description": [
            "<B>Number of Pieces:</B> 12", 
            "<B>Product Form:</B> bath bomb", 
            "<B>Scent:</B> Scented", 
            "<B>Health Facts:</B> fluoride-free, paraben-free, aluminum-free", 
            "<B>Product Warning:</B> no warning applicable", 
            "<B>Container Type:</B> Jar"
        ]
    }, 
    {
        "description": "Me! Bath Bath Bomb Papaya Nectar 6 ct is a great idea to add to a spa gift basket. These bath bombs are like scoops for your bath to make mini bath ice cream that gives you super soft skin.", 
        "dpci": "037-08-1164", 
        "brand": "Me! Bath", 
        "tcin": "18828570", 
        "images": [
            {
                "base_url": "https://target.scene7.com/is/image/Target/", 
                "primary": "18828570"
            }
        ], 
        "package_dimensions": "", 
        "categories": [
            "personal care", 
            "Skin care", 
            "Bath bombs"
        ], 
        "title": "Me! Bath Bath Bomb Papaya Nectar 6 ct", 
        "url": "/p/me-bath-bath-bomb-papaya-nectar-6-ct/-/A-18828570", 
        "release_date": "", 
        "upc": "858858000358", 
        "available_to_purchase_date_time": "", 
        "soft_bullets": {
            "bullets": [
                "Bath bomb", 
                "6 count"
            ], 
            "title": "highlights"
        }, 
        "bullet_description": [
            "<B>Product Form:</B> bath bomb", 
            "<B>Scent:</B> fruit", 
            "<B>Health Facts:</B> vegan, paraben-free, aluminum-free", 
            "<B>Product Warning:</B> no warning applicable", 
            "<B>Container Type:</B> Packet"
        ]
    }, 
    {
        "description": "Melt-A-Way Bath Candies are a sweet treat without the calories! Indulge in an ultra-moisturizing soak with Cocoa and Shea Butter bath candies. Infused with the nostalgic fragrance of Sweet & Clean and enriched with nourishing Vitamins E and C that will leave your skin silky and hydrated. A little me time is delicious, so go ahead and melt-away!", 
        "dpci": "037-08-2284", 
        "brand": "Luxe", 
        "tcin": "52592002", 
        "images": [
            {
                "content_labels": [
                    {
                        "image_url": "52592002", 
                        "displayed_in_image": {}
                    }
                ], 
                "base_url": "https://target.scene7.com/is/image/Target/", 
                "primary": "52592002"
            }
        ], 
        "package_dimensions": "", 
        "categories": [
            "personal care", 
            "Skin care", 
            "Bath bombs"
        ], 
        "title": "Luxe Melt-A-Ways Cocoa & Shea Butter Bath Candies - Sweet & Clean - 5.29oz", 
        "url": "/p/luxe-melt-a-ways-cocoa-shea-butter-bath-candies-sweet-clean-5-29oz/-/A-52592002", 
        "release_date": "", 
        "upc": "735303337187", 
        "available_to_purchase_date_time": "", 
        "soft_bullets": {
            "bullets": [
                "Melt- A-Way in a luxurious bath with Luxe by Mr. Bubble", 
                "A sweet treat without the calories", 
                "Ultra-moisturizing bath candies made with Cocoa and Shea Butters", 
                "Nourish your skin with Vitamins E and C", 
                "Soak in the sugar cream fragrance of Sweet & Clean"
            ], 
            "title": "highlights"
        }, 
        "bullet_description": [
            "<B>Number of Pieces:</B> 20", 
            "<B>Product Form:</B> bath bomb", 
            "<B>Scent:</B> Scented", 
            "<B>Health Facts:</B> paraben-free, aluminum-free", 
            "<B>Product Warning:</B> no warning applicable", 
            "<B>Container Type:</B> Box"
        ]
    }, 
    {
        "description": "Purify your senses as you unwind in a luxurious bath with Tee Tree and Sweet Orange essential oils and nourishing shea and cocoa butters. Purify Double Butter Bath Melts by Village Naturals Aromatherapy will hydrate and condition your skin with a rich blend of antioxidants and vitamins c & e. Go ahead\u2026indulge your senses.", 
        "dpci": "037-08-2286", 
        "brand": "Village Naturals", 
        "tcin": "52597407", 
        "images": [
            {
                "content_labels": [
                    {
                        "image_url": "52597407", 
                        "displayed_in_image": {}
                    }
                ], 
                "base_url": "https://target.scene7.com/is/image/Target/", 
                "primary": "52597407"
            }
        ], 
        "package_dimensions": "", 
        "categories": [
            "personal care", 
            "Skin care", 
            "Bath bombs"
        ], 
        "title": "Village Naturals Double Butter Bath Melts - Purify Tea Tree-Sweet Orange - 4.9oz", 
        "url": "/p/village-naturals-double-butter-bath-melts-purify-tea-tree-sweet-orange-4-9oz/-/A-52597407", 
        "release_date": "", 
        "upc": "735303587049", 
        "available_to_purchase_date_time": "", 
        "soft_bullets": {
            "bullets": [
                "Purify your senses with a luxurious bath", 
                "Double Butter Bath Melts provide a sophisticated experience", 
                "Drench yourself in She and Cocoa Butters that condition and hydrate skin", 
                "Relax and unwind with Tea Tree and Sweet Orange essential oils and extracts known for their ability to detoxify and protect skin"
            ], 
            "title": "highlights"
        }, 
        "bullet_description": [
            "<B>Number of Pieces:</B> 2", 
            "<B>Product Form:</B> bath bomb", 
            "<B>Scent:</B> Tea Tree, orange", 
            "<B>Health Facts:</B> paraben-free, contains tea tree oil, aluminum-free", 
            "<B>Product Warning:</B> no warning applicable", 
            "<B>Container Type:</B> Box"
        ]
    }, 
    {
        "description": "Treat yourself right tonight! Relax, unwind and have some fun with Da Bomb's Amaze Balls Mixed Fruit Bath Fizzers. Each of these colorful two-ounce balls releases gently calming ingredients and oils as they spin and fizz in your bath, soothing your skin and awakening your senses with simple, yet fragrant, components. And for added excitement, each buoyant ball has a fun toy surprise hidden inside, suitable for kids or adults of any gender.", 
        "dpci": "037-08-2134", 
        "brand": "Da Bomb Bath Fizzers", 
        "tcin": "51248767", 
        "images": [
            {
                "base_url": "https://target.scene7.com/is/image/Target/", 
                "primary": "51248767"
            }
        ], 
        "package_dimensions": "", 
        "categories": [
            "personal care", 
            "Skin care", 
            "Bath bombs"
        ], 
        "title": "Da Bomb Amaze Balls Mixed Fruit Bath Fizzer 12 oz", 
        "url": "/p/da-bomb-amaze-balls-mixed-fruit-bath-fizzer-12-oz/-/A-51248767", 
        "release_date": "", 
        "upc": "856901006135", 
        "available_to_purchase_date_time": "", 
        "soft_bullets": {
            "bullets": [
                "Fun, fragrant, fizzing bath balls", 
                "Soothe skin and awaken your senses", 
                "Fun toy surprise inside each bath fizzer", 
                "Suitable for kids and adults"
            ], 
            "title": "highlights"
        }, 
        "bullet_description": [
            "<B>Product Form:</B> bath bomb", 
            "<B>Scent:</B> fruit", 
            "<B>Health Facts:</B> vegan, hypoallergenic, phthalate-free, paraben-free, sodium lauryl sulfate-free, dye-free, aluminum-free", 
            "<B>Product Warning:</B> no warning applicable", 
            "<B>Container Type:</B> Jar"
        ]
    }, 
    {
        "description": "Pamper yourself with a moisturizing and luxurious bath! ME! Bath's Freshly Cut Roses Bath Bomb fizzes and melts in water to release a unique six oil blend, purifying minerals and indulgent fragrance.", 
        "dpci": "037-08-2367", 
        "brand": "ME! Bath", 
        "tcin": "52825207", 
        "images": [
            {
                "content_labels": [
                    {
                        "image_url": "52825207", 
                        "displayed_in_image": {}
                    }
                ], 
                "base_url": "https://target.scene7.com/is/image/Target/", 
                "primary": "52825207"
            }
        ], 
        "package_dimensions": "", 
        "categories": [
            "personal care", 
            "Skin care", 
            "Bath bombs"
        ], 
        "title": "ME! Single Freshly Cut Roses - 4oz", 
        "url": "/p/me-single-freshly-cut-roses-4oz/-/A-52825207", 
        "release_date": "", 
        "upc": "852394006652", 
        "available_to_purchase_date_time": "", 
        "soft_bullets": {
            "bullets": [
                "ME! Bath Bombs makes skin super soft!", 
                "Packed with purifying minerals & six moisturizing oils", 
                "Indulging, blooming scent of Freshly Cut Roses", 
                "Crafted in USA"
            ], 
            "title": "highlights"
        }, 
        "bullet_description": [
            "<B>Product Form:</B> bath bomb", 
            "<B>Scent:</B> rose", 
            "<B>Health Facts:</B> vegan, paraben-free, aluminum-free", 
            "<B>Product Warning:</B> Adult Use Only", 
            "<B>Container Type:</B> Box"
        ]
    }, 
    {
        "description": "Pamper yourself with a moisturizing and luxurious bath! ME! Bath's Freshly Cut Roses Bath Bombs fizz and melt in water to release a unique six oil blend, purifying minerals and indulgent fragrance.", 
        "dpci": "037-08-2366", 
        "brand": "ME! Bath", 
        "tcin": "52810351", 
        "images": [
            {
                "content_labels": [
                    {
                        "image_url": "52810351", 
                        "displayed_in_image": {}
                    }
                ], 
                "base_url": "https://target.scene7.com/is/image/Target/", 
                "primary": "52810351"
            }
        ], 
        "package_dimensions": "", 
        "categories": [
            "personal care", 
            "Skin care", 
            "Bath bombs"
        ], 
        "title": "ME! Bath Tini ME! Bath Fizzy Freshly Cut Roses - 2ct", 
        "url": "/p/me-bath-tini-me-bath-fizzy-freshly-cut-roses-2ct/-/A-52810351", 
        "release_date": "", 
        "upc": "852394006645", 
        "available_to_purchase_date_time": "", 
        "soft_bullets": {
            "bullets": [
                "ME! Bath Bombs makes skin super soft!", 
                "Packed with purifying minerals & six moisturizing oils", 
                "Indulging, blooming scent of Freshly Cut Roses", 
                "Crafted in USA"
            ], 
            "title": "highlights"
        }, 
        "bullet_description": [
            "<B>Product Form:</B> bath bomb", 
            "<B>Scent:</B> rose", 
            "<B>Health Facts:</B> vegan, paraben-free, aluminum-free", 
            "<B>Product Warning:</B> Adult Use Only", 
            "<B>Container Type:</B> gusseted bag"
        ]
    }, 
    {
        "description": "Pamper yourself with a moisturizing and luxurious bath! ME! Bath's Pink Sugar Bath Bomb fizzes and melts in water to release a unique six oil blend, purifying minerals and indulgent fragrance.", 
        "dpci": "037-08-2368", 
        "brand": "ME! Bath", 
        "tcin": "52825208", 
        "images": [
            {
                "content_labels": [
                    {
                        "image_url": "52825208", 
                        "displayed_in_image": {}
                    }
                ], 
                "base_url": "https://target.scene7.com/is/image/Target/", 
                "primary": "52825208"
            }
        ], 
        "package_dimensions": "", 
        "categories": [
            "personal care", 
            "Skin care", 
            "Bath bombs"
        ], 
        "title": "ME! Single Pink Sugar - 4oz", 
        "url": "/p/me-single-pink-sugar-4oz/-/A-52825208", 
        "release_date": "", 
        "upc": "852394006676", 
        "available_to_purchase_date_time": "", 
        "soft_bullets": {
            "bullets": [
                "ME! Bath Bombs makes skin super soft!", 
                "Packed with purifying minerals & six moisturizing oils", 
                "Pink Sugar fragrance is sweet & indulgent!", 
                "Crafted in USA"
            ], 
            "title": "highlights"
        }, 
        "bullet_description": [
            "<B>Product Form:</B> bath bomb", 
            "<B>Scent:</B> sugar", 
            "<B>Product Warning:</B> no warning applicable", 
            "<B>Container Type:</B> Box"
        ]
    }, 
    {
        "description": "Pamper yourself with a moisturizing and luxurious bath! ME! Bath's Love, ME! Bath Bombs fizz and melt in water to release a unique six oil blend, purifying minerals and indulgent fragrance.", 
        "dpci": "037-08-2365", 
        "brand": "ME! Bath", 
        "tcin": "52810350", 
        "images": [
            {
                "content_labels": [
                    {
                        "image_url": "52810350", 
                        "displayed_in_image": {}
                    }
                ], 
                "base_url": "https://target.scene7.com/is/image/Target/", 
                "primary": "52810350"
            }
        ], 
        "package_dimensions": "", 
        "categories": [
            "personal care", 
            "Skin care", 
            "Bath bombs"
        ], 
        "title": "ME! Bath Tini ME! Bath Fizzy Arrow Heart - 2ct", 
        "url": "/p/me-bath-tini-me-bath-fizzy-arrow-heart-2ct/-/A-52810350", 
        "release_date": "", 
        "upc": "852394006638", 
        "available_to_purchase_date_time": "", 
        "soft_bullets": {
            "bullets": [
                "ME! Bath Bombs makes skin super soft!", 
                "Packed with purifying minerals & six moisturizing oils", 
                "Love, ME! fragrance is a sweet fruity and floral blend", 
                "Crafted in USA"
            ], 
            "title": "highlights"
        }, 
        "bullet_description": [
            "<B>Product Form:</B> bath bomb", 
            "<B>Scent:</B> Floral", 
            "<B>Health Facts:</B> vegan, paraben-free, aluminum-free", 
            "<B>Product Warning:</B> no warning applicable", 
            "<B>Container Type:</B> gusseted bag"
        ]
    }, 
    {
        "description": "Pamper yourself with a moisturizing and luxurious bath! ME! Bath's Pink Sugar Bath Bombs fizz and melt in water to release a unique six oil blend, purifying minerals and indulgent fragrance.", 
        "dpci": "037-08-2364", 
        "brand": "ME! Bath", 
        "tcin": "52810349", 
        "images": [
            {
                "content_labels": [
                    {
                        "image_url": "52810349", 
                        "displayed_in_image": {}
                    }
                ], 
                "base_url": "https://target.scene7.com/is/image/Target/", 
                "primary": "52810349"
            }
        ], 
        "package_dimensions": "", 
        "categories": [
            "personal care", 
            "Skin care", 
            "Bath bombs"
        ], 
        "title": "ME! Bath Tini ME! Bath Fizzy Pink Sugar - 2ct", 
        "url": "/p/me-bath-tini-me-bath-fizzy-pink-sugar-2ct/-/A-52810349", 
        "release_date": "", 
        "upc": "852394006621", 
        "available_to_purchase_date_time": "", 
        "soft_bullets": {
            "bullets": [
                "ME! Bath Bombs makes skin super soft!", 
                "Packed with purifying minerals & six moisturizing oils", 
                "Pink Sugar fragrance is sweet & indulgent!", 
                "Crafted in USA"
            ], 
            "title": "highlights"
        }, 
        "bullet_description": [
            "<B>Product Form:</B> bath bomb", 
            "<B>Scent:</B> sugar", 
            "<B>Health Facts:</B> vegan, paraben-free, aluminum-free", 
            "<B>Product Warning:</B> no warning applicable", 
            "<B>Container Type:</B> gusseted bag"
        ]
    }, 
    {
        "description": "\u00c9clair Naturals Fizzy Bath Cupcake Rose Sandalwood 6 oz<br>Infused with pure sweet almond oil, vitamin E and pure botanical extracts, our Fizzy Bath Cupackes are the perfect treat for a pampering soak, with the benefits of skin moisturizing, soothing and conditioning.", 
        "dpci": "037-08-2052", 
        "brand": "Eclair Naturals", 
        "tcin": "51195279", 
        "images": [
            {
                "base_url": "https://target.scene7.com/is/image/Target/", 
                "primary": "51195279"
            }
        ], 
        "package_dimensions": "", 
        "categories": [
            "personal care", 
            "Skin care", 
            "Bath bombs"
        ], 
        "title": "Eclair Naturals Fizzy Bath Cupcake Rose Sandalwood 6 oz", 
        "url": "/p/eclair-naturals-fizzy-bath-cupcake-rose-sandalwood-6-oz/-/A-51195279", 
        "release_date": "", 
        "upc": "814691020731", 
        "available_to_purchase_date_time": "", 
        "soft_bullets": {}, 
        "bullet_description": [
            "<B>Number of Pieces:</B> 1", 
            "<B>Product Form:</B> bath bomb", 
            "<B>Scent:</B> rose, Sandalwood", 
            "<B>Health Facts:</B> ethyl alcohol-free, Contains Almond Oil, contains vitamin E, lanolin-free, phthalate-free, Sulfate-free, gluten-free, paraben-free, Petroleum-free, triclosan-free, sodium lauryl sulfate-free, DMDM Hydantoin-free, mineral oil-free, noncomedogenic, Steroid-free, artificial color-free, formaldehyde donor-free, formaldehyde-free, butylparaben-free, nonylphenol ethoxylate free, propylparaben-free, no fragrance added, vegan, aluminum-free", 
            "<B>Product Warning:</B> Adult Use Only", 
            "<B>Container Type:</B> Box"
        ]
    }, 
    {
        "description": "Unwind after a long day with this Fizz Bar Fragranced Bath Fizzer from Zoella Beauty. The rectangle bar is easy to store in your bathroom cabinet, so you can break off a square or two anytime you need some soothing relaxation. Simply toss in the bath bomb, watch it dissolve and enjoy the calming scent as you close your eyes and sink into some much needed you time.", 
        "dpci": "037-08-2063", 
        "brand": "Zoella Beauty", 
        "tcin": "51196360", 
        "images": [
            {
                "base_url": "https://target.scene7.com/is/image/Target/", 
                "primary": "51196360"
            }
        ], 
        "package_dimensions": "", 
        "categories": [
            "personal care", 
            "Skin care", 
            "Bath bombs"
        ], 
        "title": "Zoella Beauty Fizz Bar Fragranced Bath Fizzer 7 oz", 
        "url": "/p/zoella-beauty-fizz-bar-fragranced-bath-fizzer-7-oz/-/A-51196360", 
        "release_date": "", 
        "upc": "5016155119639", 
        "available_to_purchase_date_time": "", 
        "soft_bullets": {
            "bullets": [
                "&nbsp;Bath fizzes dissolve to release a soothing fragrance", 
                "&nbsp;Floral, fruity scent leaves you smelling fresh and clean", 
                "&nbsp;7oz bar contains 8 square bath bombs"
            ], 
            "title": "highlights"
        }, 
        "bullet_description": [
            "<B>Used For:</B> Fragrance", 
            "<B>Product Form:</B> bath bomb", 
            "<B>Scent:</B> Floral, fruit", 
            "<B>Product Warning:</B> Adult Use Only, use with adult supervision", 
            "<B>Container Type:</B> Packet"
        ]
    }, 
    {
        "description": "Add some fun to bath time with the SudPrize Fizzy Bath Ball. This fizzy bath bomb will turn your bath water into vibrant color without staining your tub. The fresh-smelling bath bombs fizzes up, create a nice relaxing spa time for you or the kids. An included code unlocks an interactive online game, so you can continue the fun once you're outside the bath, too.", 
        "dpci": "049-00-0050", 
        "brand": "SudBudz", 
        "tcin": "51258652", 
        "images": [
            {
                "alternate_urls": [
                    "51258652_Alt01"
                ], 
                "base_url": "https://target.scene7.com/is/image/Target/", 
                "primary": "51258652"
            }
        ], 
        "package_dimensions": "", 
        "categories": [
            "personal care", 
            "Skin care", 
            "Bath bombs"
        ], 
        "title": "SudPrize&#174; Fizzy Bath Ball - 4.2oz", 
        "url": "/p/sudprize-174-fizzy-bath-ball-4-2oz/-/A-51258652", 
        "release_date": "", 
        "upc": "867293000007", 
        "available_to_purchase_date_time": "", 
        "soft_bullets": {
            "bullets": [
                "Brings lots of fun bath time", 
                "Includes a code inside the box for an interactive online game", 
                "Colorful bath ball won't stain your bathtub"
            ], 
            "title": "highlights"
        }, 
        "bullet_description": [
            "<B>Number of Pieces:</B> 1", 
            "<B>Used For:</B> basic cleansing", 
            "<B>Product Form:</B> bath bomb", 
            "<B>Scent:</B> Fresh", 
            "<B>Product Warning:</B> no warning applicable", 
            "<B>Container Type:</B> Box"
        ]
    }, 
    {
        "description": "Nubian Heritage's Coconut & Papaya Bath Bombs invigorate, hydrate and soothe the skin. Relax as the lush, tropical scent of Coconut & Papaya envelops your senses while the transformed water cleanses and softens, leaving your skin delicately fragranced. <br><br>Directions: Fill bathtub with warm water, drop in the bath bomb and enjoy its color and fragrance. <br><br>Heritage: Since ancient times, Coconut Oil has been revered for its skin protecting and moisturizing benefits by millions in tropical communities in South America, Asia, the Caribbean and Africa. Coconut Oil contains healthy fats keeping skin soft to the touch. Papaya has been revered by natives for its skin rejuvenating properties.", 
        "dpci": "037-05-1816", 
        "brand": "Nubian Heritage", 
        "tcin": "51096969", 
        "images": [
            {
                "alternate_urls": [
                    "51096969_Alt01"
                ], 
                "base_url": "https://target.scene7.com/is/image/Target/", 
                "content_labels": [
                    {
                        "image_url": "51096969_Alt01", 
                        "displayed_in_image": {}
                    }, 
                    {
                        "image_url": "51096969", 
                        "displayed_in_image": {}
                    }
                ], 
                "primary": "51096969"
            }
        ], 
        "package_dimensions": "", 
        "categories": [
            "personal care", 
            "Skin care", 
            "Bath bombs"
        ], 
        "title": "Nubian Heritage Coconut & Papaya Bath Bombs 6 ct", 
        "url": "/p/nubian-heritage-coconut-papaya-bath-bombs-6-ct/-/A-51096969", 
        "release_date": "", 
        "upc": "764302111108", 
        "available_to_purchase_date_time": "", 
        "soft_bullets": {
            "bullets": [
                "Made with natural and certified organic ingredients.", 
                "Invigorate, hydrate and soothe the skin.", 
                "Leaves skin soft to the touch.", 
                "Leaves your skin delicately fragranced."
            ], 
            "title": "highlights"
        }, 
        "bullet_description": [
            "<B>Number of Pieces:</B> 6", 
            "<B>Product Form:</B> bath bomb", 
            "<B>Scent:</B> coconut", 
            "<B>Health Facts:</B> contains coconut, phthalate-free, Sulfate-free, butylparaben-free, sodium lauryl sulfate-free, propylparaben-free, nonylphenol ethoxylate free, formaldehyde-free, formaldehyde donor-free, paraben-free", 
            "<B>Product Warning:</B> no warning applicable", 
            "<B>Container Type:</B> Box"
        ]
    }, 
    {
        "description": "\u00c9clair Naturals Fizzy Bath Cupcake Grapefruit Orange 6 oz<br>Infused with pure sweet almond oil, vitamin E and pure botanical extracts, our Fizzy Bath Cupackes are the perfect treat for a pampering soak, with the benefits of skin moisturizing, soothing and conditioning.", 
        "dpci": "037-08-2050", 
        "brand": "Eclair Naturals", 
        "tcin": "51195274", 
        "images": [
            {
                "base_url": "https://target.scene7.com/is/image/Target/", 
                "primary": "51195274"
            }
        ], 
        "package_dimensions": "", 
        "categories": [
            "personal care", 
            "Skin care", 
            "Bath bombs"
        ], 
        "title": "Eclair Naturals Fizzy Bath Cupcake Grapefruit Orange 6 oz", 
        "url": "/p/eclair-naturals-fizzy-bath-cupcake-grapefruit-orange-6-oz/-/A-51195274", 
        "release_date": "", 
        "upc": "814691020625", 
        "available_to_purchase_date_time": "", 
        "soft_bullets": {}, 
        "bullet_description": [
            "<B>Number of Pieces:</B> 1", 
            "<B>Product Form:</B> bath bomb", 
            "<B>Scent:</B> grapefruit, orange", 
            "<B>Health Facts:</B> ethyl alcohol-free, Contains Almond Oil, contains vitamin E, DMDM Hydantoin-free, lanolin-free, noncomedogenic, Petroleum-free, phthalate-free, Steroid-free, Sulfate-free, artificial color-free, formaldehyde donor-free, gluten-free, paraben-free, sodium lauryl sulfate-free, triclosan-free, butylparaben-free, formaldehyde-free, nonylphenol ethoxylate free, propylparaben-free, no fragrance added, vegan, aluminum-free", 
            "<B>Product Warning:</B> Adult Use Only", 
            "<B>Container Type:</B> Box"
        ]
    }, 
    {
        "description": "Treat yourself to a luxurious bath experience when you immerse yourself in water infused with the African Black Soap Bath Bombs from Nubian Heritage. These bath bombs are made with natural ingredients that work together to clean, hydrate and soften while leaving your skin delicately fragranced. This pack comes with six bath bombs for multiple uses \u2014 simply pop one bath bomb into a warm tub water and settle in for a soothing and luxurious bath experience.", 
        "dpci": "037-05-1835", 
        "brand": "Nubian Heritage", 
        "tcin": "51097477", 
        "images": [
            {
                "alternate_urls": [
                    "51097477_Alt01"
                ], 
                "base_url": "https://target.scene7.com/is/image/Target/", 
                "content_labels": [
                    {
                        "image_url": "51097477", 
                        "displayed_in_image": {}
                    }, 
                    {
                        "image_url": "51097477_Alt01", 
                        "displayed_in_image": {}
                    }
                ], 
                "primary": "51097477"
            }
        ], 
        "package_dimensions": "", 
        "categories": [
            "personal care", 
            "Skin care", 
            "Bath bombs"
        ], 
        "title": "Nubian Heritage African Black Soap Bath Bombs - 6ct", 
        "url": "/p/nubian-heritage-african-black-soap-bath-bombs-6ct/-/A-51097477", 
        "release_date": "", 
        "upc": "764302106104", 
        "available_to_purchase_date_time": "", 
        "soft_bullets": {
            "bullets": [
                "Pack of 6 scented bath bombs treat you to a luxurious and relaxing spa experience", 
                "Warm, woody and musky African black soap fragrance will envelop your senses", 
                "Designed with natural ingredients to hydrate, soften and leave a delicate fragrance behind"
            ], 
            "title": "highlights"
        }, 
        "bullet_description": [
            "<B>Number of Pieces:</B> 6", 
            "<B>Product Form:</B> bath bomb", 
            "<B>Scent:</B> Aloe", 
            "<B>Health Facts:</B> Sulfate-free, formaldehyde-free, paraben-free, phthalate-free", 
            "<B>Product Warning:</B> no warning applicable", 
            "<B>Container Type:</B> Box"
        ]
    }, 
    {
        "description": "Treat yourself to a luxurious bath experience when you immerse yourself in water infused with the Indian Hemp Bath Bombs from Nubian Heritage. These bath bombs are made with natural ingredients that work together to clean, hydrate and soften while leaving your skin delicately fragranced. This pack comes with six bath bombs for multiple uses \u2014 simply pop one bath bomb into a warm tub water and settle in for a soothing and luxurious bath experience.", 
        "dpci": "037-05-1819", 
        "brand": "Nubian Heritage", 
        "tcin": "51097010", 
        "images": [
            {
                "alternate_urls": [
                    "51097010_Alt01"
                ], 
                "base_url": "https://target.scene7.com/is/image/Target/", 
                "content_labels": [
                    {
                        "image_url": "51097010", 
                        "displayed_in_image": {}
                    }, 
                    {
                        "image_url": "51097010_Alt01", 
                        "displayed_in_image": {}
                    }
                ], 
                "primary": "51097010"
            }
        ], 
        "package_dimensions": "", 
        "categories": [
            "personal care", 
            "Skin care", 
            "Bath bombs"
        ], 
        "title": "Nubian Heritage Indian Hemp Bath Bombs 6ct", 
        "url": "/p/nubian-heritage-indian-hemp-bath-bombs-6ct/-/A-51097010", 
        "release_date": "", 
        "upc": "764302111498", 
        "available_to_purchase_date_time": "", 
        "soft_bullets": {
            "bullets": [
                "Pack of 6 scented bath bombs treat you to a luxurious and relaxing spa experience", 
                "Rich, sweet and earthy Haitian Vetiver fragrance will envelop your senses", 
                "Designed with natural ingredients to hydrate, soften and leave a delicate fragrance behind"
            ], 
            "title": "highlights"
        }, 
        "bullet_description": [
            "<B>Product Form:</B> bath bomb", 
            "<B>Scent:</B> Shea", 
            "<B>Health Facts:</B> Sulfate-free, formaldehyde-free, paraben-free, phthalate-free", 
            "<B>Product Warning:</B> no warning applicable", 
            "<B>Container Type:</B> Box"
        ]
    }, 
    {
        "description": "Your skin will smell oh-so sweet and feel softer than ever after you use the Scented Bath Fizzer from Tri-Coastal Design. This purple bath bomb features a lovely gumball scent that'll awaken your senses while leaving your skin smelling delectable. It's a breeze to use - simply drop it into a tub filled with warm water and watch the bubbles come alive as the bath bomb fizzes away.", 
        "dpci": "052-17-0168", 
        "brand": "Tri-Coastal Design", 
        "tcin": "52589238", 
        "images": [
            {
                "content_labels": [
                    {
                        "image_url": "52589238", 
                        "displayed_in_image": {}
                    }
                ], 
                "base_url": "https://target.scene7.com/is/image/Target/", 
                "primary": "52589238"
            }
        ], 
        "package_dimensions": "", 
        "categories": [
            "personal care", 
            "Skin care", 
            "Bath bombs"
        ], 
        "title": "Gumball Sweets Scented Bath Bomb", 
        "url": "/p/gumball-sweets-scented-bath-bomb/-/A-52589238", 
        "release_date": "", 
        "upc": "888273953212", 
        "available_to_purchase_date_time": "", 
        "soft_bullets": {
            "bullets": [
                "Purple bath bomb is perfect for adding to a bath ritual", 
                "Scented bath bomb leaves your skin smelling like sweet gumballs", 
                "Great for adding to a bath gift set for any special occasion"
            ], 
            "title": "highlights"
        }, 
        "bullet_description": [
            "<B>Product Form:</B> bath bomb", 
            "<B>Scent:</B> Scented", 
            "<B>Product Warning:</B> no warning applicable", 
            "<B>Container Type:</B> Packet"
        ]
    }, 
    {
        "description": "Your skin will smell oh-so sweet and feel softer than ever after you use the Scented Bath Fizzer from Tri-Coastal Design. This teal bath bomb features a lovely berry scent that'll awaken your senses while leaving your skin smelling delectable. It's a breeze to use - simply drop it into a tub filled with warm water and watch the bubbles come alive as the bath bomb fizzes away.", 
        "dpci": "052-17-0171", 
        "brand": "Tri-Coastal Design", 
        "tcin": "52589242", 
        "images": [
            {
                "content_labels": [
                    {
                        "image_url": "52589242", 
                        "displayed_in_image": {}
                    }
                ], 
                "base_url": "https://target.scene7.com/is/image/Target/", 
                "primary": "52589242"
            }
        ], 
        "package_dimensions": "", 
        "categories": [
            "personal care", 
            "Skin care", 
            "Bath bombs"
        ], 
        "title": "Berry Creme Scented Bath Bomb - 5.3oz", 
        "url": "/p/berry-creme-scented-bath-bomb-5-3oz/-/A-52589242", 
        "release_date": "", 
        "upc": "888273953267", 
        "available_to_purchase_date_time": "", 
        "soft_bullets": {
            "bullets": [
                "Teal bath bomb is perfect for adding to a bath ritual", 
                "Scented bath bomb leaves your skin smelling like sweet berry creme", 
                "Great for adding to a bath gift set for any special occasion"
            ], 
            "title": "highlights"
        }, 
        "bullet_description": [
            "<B>Product Form:</B> bath bomb", 
            "<B>Scent:</B> Scented", 
            "<B>Product Warning:</B> no warning applicable", 
            "<B>Container Type:</B> Packet"
        ]
    }, 
    {
        "description": "Treat yourself to a luxurious bath experience when you immerse yourself in water infused with the Abyssinian & Chia Bath Bombs from Nubian Heritage. These bath bombs are made with natural ingredients that work together to clean, hydrate and soften while leaving your skin delicately fragranced. This pack comes with six bath bombs for multiple uses \u2014 simply pop one bath bomb into a warm tub water and settle in for a soothing and luxurious bath experience.", 
        "dpci": "037-05-1825", 
        "brand": "Nubian Heritage", 
        "tcin": "51097458", 
        "images": [
            {
                "alternate_urls": [
                    "51097458_Alt01"
                ], 
                "base_url": "https://target.scene7.com/is/image/Target/", 
                "content_labels": [
                    {
                        "image_url": "51097458", 
                        "displayed_in_image": {}
                    }, 
                    {
                        "image_url": "51097458_Alt01", 
                        "displayed_in_image": {}
                    }
                ], 
                "primary": "51097458"
            }
        ], 
        "package_dimensions": "", 
        "categories": [
            "personal care", 
            "Skin care", 
            "Bath bombs"
        ], 
        "title": "Nubian Heritage Abyssinian & Chia Bath Bombs 6ct", 
        "url": "/p/nubian-heritage-abyssinian-chia-bath-bombs-6ct/-/A-51097458", 
        "release_date": "", 
        "upc": "764302101123", 
        "available_to_purchase_date_time": "", 
        "soft_bullets": {
            "bullets": [
                "Pack of 6 scented bath bombs treat you to a luxurious and relaxing spa experience", 
                "Rich, woody and floral abyssinian and chia fragrance will envelop your senses", 
                "Designed with natural ingredients to hydrate, soften and leave a delicate fragrance behind"
            ], 
            "title": "highlights"
        }, 
        "bullet_description": [
            "<B>Product Form:</B> bath bomb", 
            "<B>Scent:</B> Scented", 
            "<B>Health Facts:</B> contains chia seeds, Sulfate-free, formaldehyde-free, paraben-free, phthalate-free", 
            "<B>Product Warning:</B> no warning applicable", 
            "<B>Container Type:</B> Box"
        ]
    }, 
    {
        "description": "Shake off the autumn chill when you hop into the tub with this toasty fizzer. Drop this 3.5-ounce sphere into your bath water and watch as it fizzes and spins, releasing skin-soothing ingredients and oils. Hold it in your hand as it dissolves because there\u2019s a fun surprise inside. Perfect for adults and kids alike. (Everyone loves surprises.) Created by a pair of teenage sisterpreneurs\u0099. Handmade in the USA using just a few, simple ingredients. <br><br>WARNING: Small parts. Not for children under 3 years.", 
        "dpci": "037-08-1627", 
        "brand": "Da Bomb Bath Fizzers", 
        "tcin": "52471564", 
        "images": [
            {
                "content_labels": [
                    {
                        "image_url": "52471564", 
                        "displayed_in_image": {}
                    }
                ], 
                "base_url": "https://target.scene7.com/is/image/Target/", 
                "primary": "52471564"
            }
        ], 
        "package_dimensions": "", 
        "categories": [
            "personal care", 
            "Skin care", 
            "Bath bombs"
        ], 
        "title": "Da Bomb Bath Fizzers&#153; Cozy Bomb&#153; Bath Soak", 
        "url": "/p/da-bomb-bath-fizzers-153-cozy-bomb-153-bath-soak/-/A-52471564", 
        "release_date": "", 
        "upc": "856901006456", 
        "available_to_purchase_date_time": "", 
        "soft_bullets": {
            "bullets": [
                "Phthalate-free", 
                "Paraben-free", 
                "SLS-free", 
                "Sulfate-free", 
                "Gluten-free", 
                "Nut-free", 
                "Cruelty-free", 
                "Vegan"
            ], 
            "title": "highlights"
        }, 
        "bullet_description": [
            "<B>Product Form:</B> bath bomb", 
            "<B>Scent:</B> Scented", 
            "<B>Health Facts:</B> paraben-free, aluminum-free, dye-free", 
            "<B>Product Warning:</B> no warning applicable", 
            "<B>Container Type:</B> Packet"
        ]
    }, 
    {
        "description": "Your skin will smell oh-so sweet and feel softer than ever after you use the Scented Bath Fizzer from Tri-Coastal Design. This white bath bomb features a lovely vanilla scent that'll awaken your senses while leaving your skin smelling delectable. It's a breeze to use - simply drop it into a tub filled with warm water and watch the bubbles come alive as the bath bomb fizzes away.", 
        "dpci": "052-17-0169", 
        "brand": "Tri-Coastal Design", 
        "tcin": "52589240", 
        "images": [
            {
                "content_labels": [
                    {
                        "image_url": "52589240", 
                        "displayed_in_image": {}
                    }
                ], 
                "base_url": "https://target.scene7.com/is/image/Target/", 
                "primary": "52589240"
            }
        ], 
        "package_dimensions": "", 
        "categories": [
            "personal care", 
            "Skin care", 
            "Bath bombs"
        ], 
        "title": "Vanilla Frost Scented Bath Bomb - 5.3oz", 
        "url": "/p/vanilla-frost-scented-bath-bomb-5-3oz/-/A-52589240", 
        "release_date": "", 
        "upc": "888273953229", 
        "available_to_purchase_date_time": "", 
        "soft_bullets": {
            "bullets": [
                "White bath bomb is perfect for adding to a bath ritual", 
                "Scented bath bomb leaves your skin smelling like sweet vanilla", 
                "Great for adding to a bath gift set for any special occasion"
            ], 
            "title": "highlights"
        }, 
        "bullet_description": [
            "<B>Product Form:</B> bath bomb", 
            "<B>Scent:</B> Scented", 
            "<B>Product Warning:</B> no warning applicable", 
            "<B>Container Type:</B> Packet"
        ]
    }, 
    {
        "description": "Your skin will smell oh-so sweet and feel softer than ever after you use the Scented Bath Fizzer from Tri-Coastal Design. This pink bath bomb features a lovely macaron scent that'll awaken your senses while leaving your skin smelling delectable. It's a breeze to use - simply drop it into a tub filled with warm water and watch the bubbles come alive as the bath bomb fizzes away.", 
        "dpci": "052-17-0170", 
        "brand": "Tri-Coastal Design", 
        "tcin": "52589241", 
        "images": [
            {
                "content_labels": [
                    {
                        "image_url": "52589241", 
                        "displayed_in_image": {}
                    }
                ], 
                "base_url": "https://target.scene7.com/is/image/Target/", 
                "primary": "52589241"
            }
        ], 
        "package_dimensions": "", 
        "categories": [
            "personal care", 
            "Skin care", 
            "Bath bombs"
        ], 
        "title": "Sweet Macaron Scented Bath Bomb - 5.3oz", 
        "url": "/p/sweet-macaron-scented-bath-bomb-5-3oz/-/A-52589241", 
        "release_date": "", 
        "upc": "888273953236", 
        "available_to_purchase_date_time": "", 
        "soft_bullets": {
            "bullets": [
                "Pink bath bomb is perfect for adding to a bath ritual", 
                "Scented bath bomb leaves your skin smelling like sweet macaron", 
                "Great for adding to a bath gift set for any special occasion"
            ], 
            "title": "highlights"
        }, 
        "bullet_description": [
            "<B>Product Form:</B> bath bomb", 
            "<B>Scent:</B> Scented", 
            "<B>Product Warning:</B> no warning applicable", 
            "<B>Container Type:</B> Packet"
        ]
    }
]